[{"Name":"###Select Consumable Name","Unit":"#Select Unit","Store_at":"#Select Place to Store.","Type":"Consumable","Stock":0},{"Name":"###Select Consumable Name","Unit":"#Select Unit","Store_at":"XRF Table Drawer","Type":"Equipment_spare_part","Stock":0},{"Name":"###Select Consumable Name","Unit":"#Select Unit","Store_at":"Microscope Table Drawer","Type":"Equipment_spare_part","Stock":0},{"Name":"###Select Consumable Name","Unit":"#Select Unit","Store_at":"OES Table Stage","Type":"Equipment_spare_part","Stock":0},{"Name":"###Select Consumable Name","Unit":"#Select Unit","Store_at":"Flame Proof Cabinet","Type":"Equipment_spare_part","Stock":0},{"Name":"###Select Consumable Name","Unit":"#Select Unit","Store_at":"Acid Fume Hood Cabinet","Type":"Equipment_spare_part","Stock":0},{"Name":"###Select Consumable Name","Unit":"#Select Unit","Store_at":"Solvent Fume Hood Cabinet","Type":"Equipment_spare_part","Stock":0},{"Name":"###Select Consumable Name","Unit":"#Select Unit","Store_at":"Balance Cabinet","Type":"Equipment_spare_part","Stock":0},{"Name":"###Select Consumable Name","Unit":"#Select Unit","Store_at":"Polisher Table Stage","Type":"Equipment_spare_part","Stock":0},{"Name":"###Select Consumable Name","Unit":"#Select Unit","Store_at":"z New Place z","Type":"Equipment_spare_part","Stock":0},{"Name":"Sandpaper - #2000Cw","Unit":"piece","Store_at":"OES Table Stage","Type":"Consumable","Stock":"2"},{"Name":"Steel Roll Sample Clip - Trojan","Unit":"piece","Store_at":"Solvent Fume Hood Cabinet","Type":"Consumable","Stock":"2"},{"Name":"Black Sample Clip - Trojan","Unit":"piece","Store_at":"Solvent Fume Hood Cabinet","Type":"Consumable","Stock":"2"},{"Name":"Plastic Roll Sample Clip - Trojan","Unit":"piece","Store_at":"Solvent Fume Hood Cabinet","Type":"Consumable","Stock":"2"},{"Name":"Sandpaper - #220Cw","Unit":"piece","Store_at":"OES Table Stage","Type":"Consumable","Stock":"2"},{"Name":"Serial Black Sample Clip - Trojan","Unit":"piece","Store_at":"Solvent Fume Hood Cabinet","Type":"Consumable","Stock":"2"},{"Name":"Acrylic Hardener - TJ2210B","Unit":"milli-liter","Store_at":"Solvent Fume Hood Cabinet","Type":"Consumable","Stock":"68"},{"Name":"Sandpaper - #660Cw","Unit":"piece","Store_at":"OES Table Stage","Type":"Consumable","Stock":"3"},{"Name":"White Sample Clip (angled) - Trojan","Unit":"piece","Store_at":"Solvent Fume Hood Cabinet","Type":"Consumable","Stock":"3"},{"Name":"Acrylic Powder - TJ2210A","Unit":"gram","Store_at":"Solvent Fume Hood Cabinet","Type":"Consumable","Stock":"160"},{"Name":"Polishing Cloth - White - Trojan","Unit":"piece","Store_at":"Solvent Fume Hood Cabinet","Type":"Consumable","Stock":"16"},{"Name":"Sandpaper - #1200Cw","Unit":"piece","Store_at":"OES Table Stage","Type":"Consumable","Stock":"4"},{"Name":"Sandpaper - #1500Cw","Unit":"piece","Store_at":"OES Table Stage","Type":"Consumable","Stock":"4"},{"Name":"Sandpaper - #800Cw","Unit":"piece","Store_at":"OES Table Stage","Type":"Consumable","Stock":"4"},{"Name":"Ethanol","Unit":"milli-liter","Store_at":"Flame Proof Cabinet","Type":"Consumable","Stock":"1630"},{"Name":"Epoxy Slow Resin","Unit":"gram","Store_at":"Flame Proof Cabinet","Type":"Consumable","Stock":"1582.25"},{"Name":"#1 microns Diamond Polishing Paste-MICRODONT","Unit":"gram","Store_at":"Solvent Fume Hood Cabinet","Type":"Consumable","Stock":"5"},{"Name":"Epoxy Slow Hardener TJ2228B","Unit":"gram","Store_at":"Flame Proof Cabinet","Type":"Consumable","Stock":"781.24"},{"Name":"Polishing Cloth - Blue - Trojan","Unit":"piece","Store_at":"Solvent Fume Hood Cabinet","Type":"Consumable","Stock":"9"},{"Name":"Amyl alcohol","Unit":"milli-liter","Store_at":"Flame Proof Cabinet","Type":"Consumable","Stock":"1850"},{"Name":"Kerosene","Unit":"milli-liter","Store_at":"Flame Proof Cabinet","Type":"Consumable","Stock":"1855"},{"Name":"Isopropyl Alcohol","Unit":"milli-liter","Store_at":"Flame Proof Cabinet","Type":"Consumable","Stock":"3310"},{"Name":"#9 microns Diamond Suspension-Trojan","Unit":"milli-liter","Store_at":"Solvent Fume Hood Cabinet","Type":"Consumable","Stock":"490"},{"Name":"Methanol","Unit":"milli-liter","Store_at":"Flame Proof Cabinet","Type":"Consumable","Stock":"1990"},{"Name":"Nitric acid","Unit":"milli-liter","Store_at":"Acid Fume Hood Cabinet","Type":"Consumable","Stock":"997.4"},{"Name":"#1 micron Diamond suspension - Trojan","Unit":"milli-liter","Store_at":"Solvent Fume Hood Cabinet","Type":"Consumable","Stock":"500"},{"Name":"#3 microns Diamond Suspension-Trojan","Unit":"milli-liter","Store_at":"Solvent Fume Hood Cabinet","Type":"Consumable","Stock":"500"},{"Name":"Belt Sandpaper - #80","Unit":"piece","Store_at":"OES Table Stage","Type":"Consumable","Stock":"5"},{"Name":"Silicon Molds dia 40mm, depth 25mm","Unit":"piece","Store_at":"Solvent Fume Hood Cabinet","Type":"Consumable","Stock":"10"},{"Name":"150ml Beaker","Unit":"piece","Store_at":"Solvent Fume Hood Cabinet","Type":"Lab_supplementary_item","Stock":"1"},{"Name":"200 ml Beaker","Unit":"piece","Store_at":"Acid Fume Hood Cabinet","Type":"Lab_supplementary_item","Stock":"2"},{"Name":"200ml Conical Flask","Unit":"piece","Store_at":"Acid Fume Hood Cabinet","Type":"Lab_supplementary_item","Stock":"1"},{"Name":"25 ml measuring cylinder (glass)","Unit":"piece","Store_at":"Acid Fume Hood Cabinet","Type":"Lab_supplementary_item","Stock":"1"},{"Name":"25 ml measuring cylinder (plastic)","Unit":"piece","Store_at":"Acid Fume Hood Cabinet","Type":"Lab_supplementary_item","Stock":"1"},{"Name":"Balance (0~300 g)","Unit":"piece","Store_at":"Solvent Fume Hood Cabinet","Type":"Lab_supplementary_item","Stock":"1"},{"Name":"Evaporating dish (90 mm)","Unit":"piece","Store_at":"Acid Fume Hood Cabinet","Type":"Lab_supplementary_item","Stock":"1"},{"Name":"Gloves (acid resistant)","Unit":"pack","Store_at":"Acid Fume Hood Cabinet","Type":"Lab_supplementary_item","Stock":"2"},{"Name":"Tweezers","Unit":"piece","Store_at":"Acid Fume Hood Cabinet","Type":"Lab_supplementary_item","Stock":"1"}]